LICENSE
MANIFEST.in
README.rst
VERSION
requirements.txt
setup.py
status_server/__init__.py
status_server/status_server.py
status_server.egg-info/PKG-INFO
status_server.egg-info/SOURCES.txt
status_server.egg-info/dependency_links.txt
status_server.egg-info/entry_points.txt
status_server.egg-info/requires.txt
status_server.egg-info/top_level.txt