Metadata-Version: 1.1
Name: status-server
Version: 0.0.0
Summary: Serve HTTP statuses by URL
Home-page: https://github.com/charlesthomas/status_server
Author: Charles Thomas
Author-email: ch@rlesthom.as
License: The MIT License (MIT)
